Jenkinsfile
LICENSE
MANIFEST.in
Makefile
README.md
blindecdh.spec
build.parameters
mypy.ini
pyproject.toml
setup.cfg
tox.ini
src/blindecdh/__init__.py
src/blindecdh/py.typed
src/blindecdh.egg-info/PKG-INFO
src/blindecdh.egg-info/SOURCES.txt
src/blindecdh.egg-info/dependency_links.txt
src/blindecdh.egg-info/requires.txt
src/blindecdh.egg-info/top_level.txt
tests/conftest.py
tests/test_package.py